{"ongoing_trials": {}, "hyperparameters": {"space": [{"class_name": "Int", "config": {"name": "units_1", "default": null, "conditions": [], "min_value": 32, "max_value": 256, "step": 32, "sampling": "linear"}}, {"class_name": "Choice", "config": {"name": "return_sequences", "default": 1, "conditions": [], "values": [1, 0], "ordered": true}}, {"class_name": "Int", "config": {"name": "units_2", "default": null, "conditions": [], "min_value": 32, "max_value": 256, "step": 32, "sampling": "linear"}}, {"class_name": "Float", "config": {"name": "dropout", "default": 0.1, "conditions": [], "min_value": 0.1, "max_value": 0.3, "step": 0.1, "sampling": "linear"}}], "values": {"units_1": 32, "return_sequences": 1, "units_2": 32, "dropout": 0.1}}, "start_order": ["0", "1", "2", "3", "4"], "end_order": ["0", "1", "2", "3", "4"], "run_times": {"0": 1, "1": 1, "2": 1, "3": 1, "4": 1}, "retry_queue": [], "seed": 3845, "seed_state": 3865, "tried_so_far": ["99ad17f415b880419515b0f3c9ec83a0", "2c70f2afb579bd4d207dca1ba90454b9", "682e2ef7b6c94fb131ea00a3eda40586", "5e3e69048a2b6f54430f0177ab3a3154", "87f95da4bf42dea4f33b21d61930ee6c"], "id_to_hash": {"0": "5e3e69048a2b6f54430f0177ab3a3154", "1": "99ad17f415b880419515b0f3c9ec83a0", "2": "2c70f2afb579bd4d207dca1ba90454b9", "3": "87f95da4bf42dea4f33b21d61930ee6c", "4": "682e2ef7b6c94fb131ea00a3eda40586"}, "display": {"search_start": "2024-04-12T14:14:34.409814", "trial_start": {"0": "2024-04-12T14:14:34.409814", "1": "2024-04-12T14:15:16.546908", "2": "2024-04-12T14:15:56.484907", "3": "2024-04-12T14:17:04.610167", "4": "2024-04-12T14:17:47.285597"}, "trial_number": {"0": 1, "1": 2, "2": 3, "3": 4, "4": 5}}}